lektor_git_src_publisher.py
lektor_git_src_publisher-0.1.dist-info/LICENSE
lektor_git_src_publisher-0.1.dist-info/METADATA
lektor_git_src_publisher-0.1.dist-info/WHEEL
lektor_git_src_publisher-0.1.dist-info/entry_points.txt
lektor_git_src_publisher-0.1.dist-info/top_level.txt
lektor_git_src_publisher-0.1.dist-info/RECORD
