Metadata-Version: 2.1
Name: lektor-git-src-publisher
Version: 0.1
Summary: Simple plugin to use Lektor to abstract away git usage.
Home-page: https://github.com/CamilionEU/lektor-git-src-publisher
Author: Andrés
Author-email: andres+cvs@camilion.eu
License: MIT
Keywords: Lektor plugin
Platform: UNKNOWN
Classifier: Framework :: Lektor
Classifier: Environment :: Web Environment
Classifier: Environment :: Plugins
Classifier: License :: OSI Approved :: MIT License
